odoo/addons/l10n_cl_sii_activity/README.rst
odoo/addons/l10n_cl_sii_activity/__init__.py
odoo/addons/l10n_cl_sii_activity/__manifest__.py
odoo/addons/l10n_cl_sii_activity/data/sii.activity.csv
odoo/addons/l10n_cl_sii_activity/i18n/es_CL.po
odoo/addons/l10n_cl_sii_activity/i18n/l10n_cl_sii_activity.pot
odoo/addons/l10n_cl_sii_activity/models/__init__.py
odoo/addons/l10n_cl_sii_activity/models/res_partner.py
odoo/addons/l10n_cl_sii_activity/models/sii_activity.py
odoo/addons/l10n_cl_sii_activity/readme/CONTRIBUTORS.rst
odoo/addons/l10n_cl_sii_activity/readme/DESCRIPTION.rst
odoo/addons/l10n_cl_sii_activity/readme/USAGE.rst
odoo/addons/l10n_cl_sii_activity/security/ir.model.access.csv
odoo/addons/l10n_cl_sii_activity/static/description/icon.png
odoo/addons/l10n_cl_sii_activity/static/description/index.html
odoo/addons/l10n_cl_sii_activity/views/res_partner.xml
odoo/addons/l10n_cl_sii_activity/views/sii_activity.xml
odoo12_addon_l10n_cl_sii_activity-12.0.1.2.0.dist-info/METADATA
odoo12_addon_l10n_cl_sii_activity-12.0.1.2.0.dist-info/WHEEL
odoo12_addon_l10n_cl_sii_activity-12.0.1.2.0.dist-info/top_level.txt
odoo12_addon_l10n_cl_sii_activity-12.0.1.2.0.dist-info/RECORD
