Metadata-Version: 2.1
Name: odoo12-addon-l10n-cl-sii-activity
Version: 12.0.1.2.0
Summary: Set the SII Activity on Partners
Home-page: https://github.com/OCA/l10n-chile
Author: Daniel Blanco, Blanco Martín & Asociados, Daniel Santibáñez Polanco, Cooperativa OdooCoop, Konos, Open Source Integrators, Odoo Community Association (OCA)
Author-email: support@odoo-community.org
License: AGPL-3
Platform: UNKNOWN
Classifier: Programming Language :: Python
Classifier: Framework :: Odoo
Classifier: License :: OSI Approved :: GNU Affero General Public License v3
Classifier: Development Status :: 4 - Beta
Requires-Python: >=3.5
Requires-Dist: odoo (<12.1dev,>=12.0a)
